EmailTemplate/__init__.py
EmailTemplate/admin.py
EmailTemplate/models.py
EmailTemplate/tests.py
EmailTemplate/views.py
EmailTemplate/migrations/0001_initial.py
EmailTemplate/migrations/0002_auto_20190719_1354.py
EmailTemplate/migrations/0003_auto_20190719_1358.py
EmailTemplate/migrations/0004_auto_20210226_0911.py
EmailTemplate/migrations/0005_emailtemplate_bcc_emailtemplate_cc.py
EmailTemplate/migrations/0006_alter_emailtemplate_id_emaillog.py
EmailTemplate/migrations/__init__.py
django_proemail_template-0.2.7.dist-info/LICENSE
django_proemail_template-0.2.7.dist-info/METADATA
django_proemail_template-0.2.7.dist-info/WHEEL
django_proemail_template-0.2.7.dist-info/top_level.txt
django_proemail_template-0.2.7.dist-info/RECORD
